[
    {
        "day": "08/04",
        "hour": "21",
        "main": {
            "feels_like": 27.02,
            "grnd_level": 973,
            "humidity": 85,
            "pressure": 1014,
            "sea_level": 1015,
            "temp": 23.55,
            "temp_kf": 3.62,
            "temp_max": 23.55,
            "temp_min": 19.93
        },
        "time": "08/04 21",
        "weather": {
            "description": "曇りがち",
            "icon": "https://openweathermap.org/img/wn/04n@2x.png",
            "id": 803,
            "main": "Clouds"
        }
    },
    {
        "day": "08/05",
        "hour": "00",
        "main": {
            "feels_like": 25,
            "grnd_level": 974,
            "humidity": 86,
            "pressure": 1015,
            "sea_level": 1015,
            "temp": 21.88,
            "temp_kf": 1.41,
            "temp_max": 21.88,
            "temp_min": 20.47
        },
        "time": "08/05 00",
        "weather": {
            "description": "厚い雲",
            "icon": "https://openweathermap.org/img/wn/04n@2x.png",
            "id": 804,
            "main": "Clouds"
        }
    },
    {
        "day": "08/05",
        "hour": "03",
        "main": {
            "feels_like": 23.06,
            "grnd_level": 974,
            "humidity": 92,
            "pressure": 1015,
            "sea_level": 1015,
            "temp": 20.29,
            "temp_kf": 0.46,
            "temp_max": 20.29,
            "temp_min": 19.83
        },
        "time": "08/05 03",
        "weather": {
            "description": "厚い雲",
            "icon": "https://openweathermap.org/img/wn/04n@2x.png",
            "id": 804,
            "main": "Clouds"
        }
    },
    {
        "day": "08/05",
        "hour": "06",
        "main": {
            "feels_like": 23.59,
            "grnd_level": 975,
            "humidity": 88,
            "pressure": 1016,
            "sea_level": 1016,
            "temp": 21.1,
            "temp_kf": 0.05,
            "temp_max": 21.1,
            "temp_min": 21.05
        },
        "time": "08/05 06",
        "weather": {
            "description": "厚い雲",
            "icon": "https://openweathermap.org/img/wn/04d@2x.png",
            "id": 804,
            "main": "Clouds"
        }
    },
    {
        "day": "08/05",
        "hour": "09",
        "main": {
            "feels_like": 26.6,
            "grnd_level": 975,
            "humidity": 76,
            "pressure": 1016,
            "sea_level": 1016,
            "temp": 24.03,
            "temp_kf": 0,
            "temp_max": 24.03,
            "temp_min": 24.03
        },
        "time": "08/05 09",
        "weather": {
            "description": "厚い雲",
            "icon": "https://openweathermap.org/img/wn/04d@2x.png",
            "id": 804,
            "main": "Clouds"
        }
    },
    {
        "day": "08/05",
        "hour": "12",
        "main": {
            "feels_like": 27.81,
            "grnd_level": 976,
            "humidity": 60,
            "pressure": 1016,
            "sea_level": 1016,
            "temp": 27.46,
            "temp_kf": 0,
            "temp_max": 27.46,
            "temp_min": 27.46
        },
        "time": "08/05 12",
        "weather": {
            "description": "厚い雲",
            "icon": "https://openweathermap.org/img/wn/04d@2x.png",
            "id": 804,
            "main": "Clouds"
        }
    },
    {
        "day": "08/05",
        "hour": "15",
        "main": {
            "feels_like": 27.04,
            "grnd_level": 974,
            "humidity": 63,
            "pressure": 1015,
            "sea_level": 1015,
            "temp": 26.22,
            "temp_kf": 0,
            "temp_max": 26.22,
            "temp_min": 26.22
        },
        "time": "08/05 15",
        "weather": {
            "description": "厚い雲",
            "icon": "https://openweathermap.org/img/wn/04d@2x.png",
            "id": 804,
            "main": "Clouds"
        }
    },
    {
        "day": "08/05",
        "hour": "18",
        "main": {
            "feels_like": 26.3,
            "grnd_level": 975,
            "humidity": 86,
            "pressure": 1016,
            "sea_level": 1016,
            "temp": 23.11,
            "temp_kf": 0,
            "temp_max": 23.11,
            "temp_min": 23.11
        },
        "time": "08/05 18",
        "weather": {
            "description": "曇りがち",
            "icon": "https://openweathermap.org/img/wn/04d@2x.png",
            "id": 803,
            "main": "Clouds"
        }
    },
    {
        "day": "08/05",
        "hour": "21",
        "main": {
            "feels_like": 22.88,
            "grnd_level": 974,
            "humidity": 95,
            "pressure": 1016,
            "sea_level": 1016,
            "temp": 20.09,
            "temp_kf": 0,
            "temp_max": 20.09,
            "temp_min": 20.09
        },
        "time": "08/05 21",
        "weather": {
            "description": "曇りがち",
            "icon": "https://openweathermap.org/img/wn/04n@2x.png",
            "id": 803,
            "main": "Clouds"
        }
    },
    {
        "day": "08/06",
        "hour": "00",
        "main": {
            "feels_like": 22.24,
            "grnd_level": 975,
            "humidity": 91,
            "pressure": 1016,
            "sea_level": 1016,
            "temp": 19.77,
            "temp_kf": 0,
            "temp_max": 19.77,
            "temp_min": 19.77
        },
        "time": "08/06 00",
        "weather": {
            "description": "曇りがち",
            "icon": "https://openweathermap.org/img/wn/04n@2x.png",
            "id": 803,
            "main": "Clouds"
        }
    },
    {
        "day": "08/06",
        "hour": "03",
        "main": {
            "feels_like": 21.02,
            "grnd_level": 973,
            "humidity": 90,
            "pressure": 1014,
            "sea_level": 1014,
            "temp": 19.14,
            "temp_kf": 0,
            "temp_max": 19.14,
            "temp_min": 19.14
        },
        "time": "08/06 03",
        "weather": {
            "description": "曇りがち",
            "icon": "https://openweathermap.org/img/wn/04n@2x.png",
            "id": 803,
            "main": "Clouds"
        }
    },
    {
        "day": "08/06",
        "hour": "06",
        "main": {
            "feels_like": 23.75,
            "grnd_level": 974,
            "humidity": 86,
            "pressure": 1015,
            "sea_level": 1015,
            "temp": 21.28,
            "temp_kf": 0,
            "temp_max": 21.28,
            "temp_min": 21.28
        },
        "time": "08/06 06",
        "weather": {
            "description": "曇りがち",
            "icon": "https://openweathermap.org/img/wn/04d@2x.png",
            "id": 803,
            "main": "Clouds"
        }
    },
    {
        "day": "08/06",
        "hour": "09",
        "main": {
            "feels_like": 32.04,
            "grnd_level": 974,
            "humidity": 63,
            "pressure": 1015,
            "sea_level": 1015,
            "temp": 28.48,
            "temp_kf": 0,
            "temp_max": 28.48,
            "temp_min": 28.48
        },
        "time": "08/06 09",
        "weather": {
            "description": "曇りがち",
            "icon": "https://openweathermap.org/img/wn/04d@2x.png",
            "id": 803,
            "main": "Clouds"
        }
    },
    {
        "day": "08/06",
        "hour": "12",
        "main": {
            "feels_like": 32.57,
            "grnd_level": 974,
            "humidity": 45,
            "pressure": 1014,
            "sea_level": 1014,
            "temp": 31.16,
            "temp_kf": 0,
            "temp_max": 31.16,
            "temp_min": 31.16
        },
        "time": "08/06 12",
        "weather": {
            "description": "曇りがち",
            "icon": "https://openweathermap.org/img/wn/04d@2x.png",
            "id": 803,
            "main": "Clouds"
        }
    },
    {
        "day": "08/06",
        "hour": "15",
        "main": {
            "feels_like": 32.89,
            "grnd_level": 972,
            "humidity": 59,
            "pressure": 1012,
            "sea_level": 1012,
            "temp": 29.42,
            "temp_kf": 0,
            "temp_max": 29.42,
            "temp_min": 29.42
        },
        "time": "08/06 15",
        "weather": {
            "description": "曇りがち",
            "icon": "https://openweathermap.org/img/wn/04d@2x.png",
            "id": 803,
            "main": "Clouds"
        }
    },
    {
        "day": "08/06",
        "hour": "18",
        "main": {
            "feels_like": 29.32,
            "grnd_level": 972,
            "humidity": 77,
            "pressure": 1012,
            "sea_level": 1012,
            "temp": 25.33,
            "temp_kf": 0,
            "temp_max": 25.33,
            "temp_min": 25.33
        },
        "time": "08/06 18",
        "weather": {
            "description": "厚い雲",
            "icon": "https://openweathermap.org/img/wn/04d@2x.png",
            "id": 804,
            "main": "Clouds"
        }
    },
    {
        "day": "08/06",
        "hour": "21",
        "main": {
            "feels_like": 24.06,
            "grnd_level": 971,
            "humidity": 88,
            "pressure": 1012,
            "sea_level": 1012,
            "temp": 21.62,
            "temp_kf": 0,
            "temp_max": 21.62,
            "temp_min": 21.62
        },
        "time": "08/06 21",
        "weather": {
            "description": "小雨",
            "icon": "https://openweathermap.org/img/wn/10n@2x.png",
            "id": 500,
            "main": "Rain"
        }
    },
    {
        "day": "08/07",
        "hour": "00",
        "main": {
            "feels_like": 22.01,
            "grnd_level": 970,
            "humidity": 92,
            "pressure": 1011,
            "sea_level": 1011,
            "temp": 20.18,
            "temp_kf": 0,
            "temp_max": 20.18,
            "temp_min": 20.18
        },
        "time": "08/07 00",
        "weather": {
            "description": "厚い雲",
            "icon": "https://openweathermap.org/img/wn/04n@2x.png",
            "id": 804,
            "main": "Clouds"
        }
    },
    {
        "day": "08/07",
        "hour": "03",
        "main": {
            "feels_like": 21.19,
            "grnd_level": 967,
            "humidity": 93,
            "pressure": 1008,
            "sea_level": 1008,
            "temp": 19.64,
            "temp_kf": 0,
            "temp_max": 19.64,
            "temp_min": 19.64
        },
        "time": "08/07 03",
        "weather": {
            "description": "小雨",
            "icon": "https://openweathermap.org/img/wn/10n@2x.png",
            "id": 500,
            "main": "Rain"
        }
    },
    {
        "day": "08/07",
        "hour": "06",
        "main": {
            "feels_like": 23.91,
            "grnd_level": 967,
            "humidity": 92,
            "pressure": 1008,
            "sea_level": 1008,
            "temp": 21.45,
            "temp_kf": 0,
            "temp_max": 21.45,
            "temp_min": 21.45
        },
        "time": "08/07 06",
        "weather": {
            "description": "厚い雲",
            "icon": "https://openweathermap.org/img/wn/04d@2x.png",
            "id": 804,
            "main": "Clouds"
        }
    },
    {
        "day": "08/07",
        "hour": "09",
        "main": {
            "feels_like": 27.43,
            "grnd_level": 967,
            "humidity": 76,
            "pressure": 1007,
            "sea_level": 1007,
            "temp": 25.6,
            "temp_kf": 0,
            "temp_max": 25.6,
            "temp_min": 25.6
        },
        "time": "08/07 09",
        "weather": {
            "description": "厚い雲",
            "icon": "https://openweathermap.org/img/wn/04d@2x.png",
            "id": 804,
            "main": "Clouds"
        }
    },
    {
        "day": "08/07",
        "hour": "12",
        "main": {
            "feels_like": 25.08,
            "grnd_level": 966,
            "humidity": 89,
            "pressure": 1006,
            "sea_level": 1006,
            "temp": 23.94,
            "temp_kf": 0,
            "temp_max": 23.94,
            "temp_min": 23.94
        },
        "time": "08/07 12",
        "weather": {
            "description": "小雨",
            "icon": "https://openweathermap.org/img/wn/10d@2x.png",
            "id": 500,
            "main": "Rain"
        }
    },
    {
        "day": "08/07",
        "hour": "15",
        "main": {
            "feels_like": 21.58,
            "grnd_level": 965,
            "humidity": 97,
            "pressure": 1006,
            "sea_level": 1006,
            "temp": 21.7,
            "temp_kf": 0,
            "temp_max": 21.7,
            "temp_min": 21.7
        },
        "time": "08/07 15",
        "weather": {
            "description": "適度な雨",
            "icon": "https://openweathermap.org/img/wn/10d@2x.png",
            "id": 501,
            "main": "Rain"
        }
    },
    {
        "day": "08/07",
        "hour": "18",
        "main": {
            "feels_like": 22.74,
            "grnd_level": 966,
            "humidity": 99,
            "pressure": 1007,
            "sea_level": 1007,
            "temp": 21.14,
            "temp_kf": 0,
            "temp_max": 21.14,
            "temp_min": 21.14
        },
        "time": "08/07 18",
        "weather": {
            "description": "適度な雨",
            "icon": "https://openweathermap.org/img/wn/10d@2x.png",
            "id": 501,
            "main": "Rain"
        }
    },
    {
        "day": "08/07",
        "hour": "21",
        "main": {
            "feels_like": 23.7,
            "grnd_level": 967,
            "humidity": 99,
            "pressure": 1008,
            "sea_level": 1008,
            "temp": 20.86,
            "temp_kf": 0,
            "temp_max": 20.86,
            "temp_min": 20.86
        },
        "time": "08/07 21",
        "weather": {
            "description": "適度な雨",
            "icon": "https://openweathermap.org/img/wn/10n@2x.png",
            "id": 501,
            "main": "Rain"
        }
    },
    {
        "day": "08/08",
        "hour": "00",
        "main": {
            "feels_like": 23.39,
            "grnd_level": 967,
            "humidity": 99,
            "pressure": 1008,
            "sea_level": 1008,
            "temp": 20.34,
            "temp_kf": 0,
            "temp_max": 20.34,
            "temp_min": 20.34
        },
        "time": "08/08 00",
        "weather": {
            "description": "適度な雨",
            "icon": "https://openweathermap.org/img/wn/10n@2x.png",
            "id": 501,
            "main": "Rain"
        }
    },
    {
        "day": "08/08",
        "hour": "03",
        "main": {
            "feels_like": 23.33,
            "grnd_level": 966,
            "humidity": 98,
            "pressure": 1007,
            "sea_level": 1007,
            "temp": 20.09,
            "temp_kf": 0,
            "temp_max": 20.09,
            "temp_min": 20.09
        },
        "time": "08/08 03",
        "weather": {
            "description": "適度な雨",
            "icon": "https://openweathermap.org/img/wn/10n@2x.png",
            "id": 501,
            "main": "Rain"
        }
    },
    {
        "day": "08/08",
        "hour": "06",
        "main": {
            "feels_like": 24.02,
            "grnd_level": 967,
            "humidity": 98,
            "pressure": 1008,
            "sea_level": 1008,
            "temp": 20.72,
            "temp_kf": 0,
            "temp_max": 20.72,
            "temp_min": 20.72
        },
        "time": "08/08 06",
        "weather": {
            "description": "小雨",
            "icon": "https://openweathermap.org/img/wn/10d@2x.png",
            "id": 500,
            "main": "Rain"
        }
    },
    {
        "day": "08/08",
        "hour": "09",
        "main": {
            "feels_like": 24.7,
            "grnd_level": 968,
            "humidity": 97,
            "pressure": 1009,
            "sea_level": 1009,
            "temp": 21.74,
            "temp_kf": 0,
            "temp_max": 21.74,
            "temp_min": 21.74
        },
        "time": "08/08 09",
        "weather": {
            "description": "適度な雨",
            "icon": "https://openweathermap.org/img/wn/10d@2x.png",
            "id": 501,
            "main": "Rain"
        }
    },
    {
        "day": "08/08",
        "hour": "12",
        "main": {
            "feels_like": 25.24,
            "grnd_level": 968,
            "humidity": 97,
            "pressure": 1008,
            "sea_level": 1008,
            "temp": 21.6,
            "temp_kf": 0,
            "temp_max": 21.6,
            "temp_min": 21.6
        },
        "time": "08/08 12",
        "weather": {
            "description": "小雨",
            "icon": "https://openweathermap.org/img/wn/10d@2x.png",
            "id": 500,
            "main": "Rain"
        }
    },
    {
        "day": "08/08",
        "hour": "15",
        "main": {
            "feels_like": 26.62,
            "grnd_level": 967,
            "humidity": 92,
            "pressure": 1008,
            "sea_level": 1008,
            "temp": 23.34,
            "temp_kf": 0,
            "temp_max": 23.34,
            "temp_min": 23.34
        },
        "time": "08/08 15",
        "weather": {
            "description": "小雨",
            "icon": "https://openweathermap.org/img/wn/10d@2x.png",
            "id": 500,
            "main": "Rain"
        }
    },
    {
        "day": "08/08",
        "hour": "18",
        "main": {
            "feels_like": 24.63,
            "grnd_level": 967,
            "humidity": 96,
            "pressure": 1008,
            "sea_level": 1008,
            "temp": 21.33,
            "temp_kf": 0,
            "temp_max": 21.33,
            "temp_min": 21.33
        },
        "time": "08/08 18",
        "weather": {
            "description": "小雨",
            "icon": "https://openweathermap.org/img/wn/10d@2x.png",
            "id": 500,
            "main": "Rain"
        }
    },
    {
        "day": "08/08",
        "hour": "21",
        "main": {
            "feels_like": 24.15,
            "grnd_level": 968,
            "humidity": 98,
            "pressure": 1009,
            "sea_level": 1009,
            "temp": 20.76,
            "temp_kf": 0,
            "temp_max": 20.76,
            "temp_min": 20.76
        },
        "time": "08/08 21",
        "weather": {
            "description": "小雨",
            "icon": "https://openweathermap.org/img/wn/10n@2x.png",
            "id": 500,
            "main": "Rain"
        }
    },
    {
        "day": "08/09",
        "hour": "00",
        "main": {
            "feels_like": 23.1,
            "grnd_level": 967,
            "humidity": 99,
            "pressure": 1008,
            "sea_level": 1008,
            "temp": 20.48,
            "temp_kf": 0,
            "temp_max": 20.48,
            "temp_min": 20.48
        },
        "time": "08/09 00",
        "weather": {
            "description": "適度な雨",
            "icon": "https://openweathermap.org/img/wn/10n@2x.png",
            "id": 501,
            "main": "Rain"
        }
    },
    {
        "day": "08/09",
        "hour": "03",
        "main": {
            "feels_like": 23.31,
            "grnd_level": 966,
            "humidity": 99,
            "pressure": 1006,
            "sea_level": 1006,
            "temp": 20.3,
            "temp_kf": 0,
            "temp_max": 20.3,
            "temp_min": 20.3
        },
        "time": "08/09 03",
        "weather": {
            "description": "強い雨",
            "icon": "https://openweathermap.org/img/wn/10n@2x.png",
            "id": 502,
            "main": "Rain"
        }
    },
    {
        "day": "08/09",
        "hour": "06",
        "main": {
            "feels_like": 22.86,
            "grnd_level": 965,
            "humidity": 99,
            "pressure": 1006,
            "sea_level": 1006,
            "temp": 20.2,
            "temp_kf": 0,
            "temp_max": 20.2,
            "temp_min": 20.2
        },
        "time": "08/09 06",
        "weather": {
            "description": "強い雨",
            "icon": "https://openweathermap.org/img/wn/10d@2x.png",
            "id": 502,
            "main": "Rain"
        }
    },
    {
        "day": "08/09",
        "hour": "09",
        "main": {
            "feels_like": 23.33,
            "grnd_level": 965,
            "humidity": 99,
            "pressure": 1006,
            "sea_level": 1006,
            "temp": 20.55,
            "temp_kf": 0,
            "temp_max": 20.55,
            "temp_min": 20.55
        },
        "time": "08/09 09",
        "weather": {
            "description": "強い雨",
            "icon": "https://openweathermap.org/img/wn/10d@2x.png",
            "id": 502,
            "main": "Rain"
        }
    },
    {
        "day": "08/09",
        "hour": "12",
        "main": {
            "feels_like": 24.21,
            "grnd_level": 965,
            "humidity": 99,
            "pressure": 1006,
            "sea_level": 1006,
            "temp": 21.05,
            "temp_kf": 0,
            "temp_max": 21.05,
            "temp_min": 21.05
        },
        "time": "08/09 12",
        "weather": {
            "description": "適度な雨",
            "icon": "https://openweathermap.org/img/wn/10d@2x.png",
            "id": 501,
            "main": "Rain"
        }
    },
    {
        "day": "08/09",
        "hour": "15",
        "main": {
            "feels_like": 25.55,
            "grnd_level": 966,
            "humidity": 98,
            "pressure": 1007,
            "sea_level": 1007,
            "temp": 22.31,
            "temp_kf": 0,
            "temp_max": 22.31,
            "temp_min": 22.31
        },
        "time": "08/09 15",
        "weather": {
            "description": "適度な雨",
            "icon": "https://openweathermap.org/img/wn/10d@2x.png",
            "id": 501,
            "main": "Rain"
        }
    },
    {
        "day": "08/09",
        "hour": "18",
        "main": {
            "feels_like": 24.69,
            "grnd_level": 967,
            "humidity": 99,
            "pressure": 1008,
            "sea_level": 1008,
            "temp": 21.97,
            "temp_kf": 0,
            "temp_max": 21.97,
            "temp_min": 21.97
        },
        "time": "08/09 18",
        "weather": {
            "description": "小雨",
            "icon": "https://openweathermap.org/img/wn/10d@2x.png",
            "id": 500,
            "main": "Rain"
        }
    }
]