[
    {
        "day": "04/15",
        "hour": "06",
        "main": {
            "feels_like": -2.21,
            "grnd_level": 932,
            "humidity": 71,
            "pressure": 1010,
            "sea_level": 1010,
            "temp": 2.31,
            "temp_kf": 0,
            "temp_max": 2.31,
            "temp_min": 2.31
        },
        "time": "04/15 06",
        "weather": {
            "description": "雲",
            "icon": "https://openweathermap.org/img/wn/03d@2x.png",
            "id": 802,
            "main": "Clouds"
        }
    },
    {
        "day": "04/15",
        "hour": "09",
        "main": {
            "feels_like": 0.65,
            "grnd_level": 932,
            "humidity": 61,
            "pressure": 1009,
            "sea_level": 1009,
            "temp": 6.42,
            "temp_kf": 0,
            "temp_max": 6.42,
            "temp_min": 6.42
        },
        "time": "04/15 09",
        "weather": {
            "description": "曇りがち",
            "icon": "https://openweathermap.org/img/wn/04d@2x.png",
            "id": 803,
            "main": "Clouds"
        }
    },
    {
        "day": "04/15",
        "hour": "12",
        "main": {
            "feels_like": 0.71,
            "grnd_level": 932,
            "humidity": 60,
            "pressure": 1008,
            "sea_level": 1008,
            "temp": 8.09,
            "temp_kf": 0,
            "temp_max": 8.09,
            "temp_min": 8.09
        },
        "time": "04/15 12",
        "weather": {
            "description": "曇りがち",
            "icon": "https://openweathermap.org/img/wn/04d@2x.png",
            "id": 803,
            "main": "Clouds"
        }
    },
    {
        "day": "04/15",
        "hour": "15",
        "main": {
            "feels_like": 0.16,
            "grnd_level": 931,
            "humidity": 65,
            "pressure": 1008,
            "sea_level": 1008,
            "temp": 6.59,
            "temp_kf": 0,
            "temp_max": 6.59,
            "temp_min": 6.59
        },
        "time": "04/15 15",
        "weather": {
            "description": "小雨",
            "icon": "https://openweathermap.org/img/wn/10d@2x.png",
            "id": 500,
            "main": "Rain"
        }
    },
    {
        "day": "04/15",
        "hour": "18",
        "main": {
            "feels_like": -1.16,
            "grnd_level": 933,
            "humidity": 64,
            "pressure": 1011,
            "sea_level": 1011,
            "temp": 3.37,
            "temp_kf": 0,
            "temp_max": 3.37,
            "temp_min": 3.37
        },
        "time": "04/15 18",
        "weather": {
            "description": "薄い雲",
            "icon": "https://openweathermap.org/img/wn/02d@2x.png",
            "id": 801,
            "main": "Clouds"
        }
    },
    {
        "day": "04/15",
        "hour": "21",
        "main": {
            "feels_like": -3.7,
            "grnd_level": 935,
            "humidity": 76,
            "pressure": 1014,
            "sea_level": 1014,
            "temp": -0.31,
            "temp_kf": 0,
            "temp_max": -0.31,
            "temp_min": -0.31
        },
        "time": "04/15 21",
        "weather": {
            "description": "薄い雲",
            "icon": "https://openweathermap.org/img/wn/02n@2x.png",
            "id": 801,
            "main": "Clouds"
        }
    },
    {
        "day": "04/16",
        "hour": "00",
        "main": {
            "feels_like": -4.31,
            "grnd_level": 936,
            "humidity": 78,
            "pressure": 1015,
            "sea_level": 1015,
            "temp": -0.95,
            "temp_kf": 0,
            "temp_max": -0.95,
            "temp_min": -0.95
        },
        "time": "04/16 00",
        "weather": {
            "description": "薄い雲",
            "icon": "https://openweathermap.org/img/wn/02n@2x.png",
            "id": 801,
            "main": "Clouds"
        }
    },
    {
        "day": "04/16",
        "hour": "03",
        "main": {
            "feels_like": -4.73,
            "grnd_level": 936,
            "humidity": 79,
            "pressure": 1015,
            "sea_level": 1015,
            "temp": -1.24,
            "temp_kf": 0,
            "temp_max": -1.24,
            "temp_min": -1.24
        },
        "time": "04/16 03",
        "weather": {
            "description": "雲",
            "icon": "https://openweathermap.org/img/wn/03n@2x.png",
            "id": 802,
            "main": "Clouds"
        }
    },
    {
        "day": "04/16",
        "hour": "06",
        "main": {
            "feels_like": -4.45,
            "grnd_level": 938,
            "humidity": 75,
            "pressure": 1017,
            "sea_level": 1017,
            "temp": -0.65,
            "temp_kf": 0,
            "temp_max": -0.65,
            "temp_min": -0.65
        },
        "time": "04/16 06",
        "weather": {
            "description": "雲",
            "icon": "https://openweathermap.org/img/wn/03d@2x.png",
            "id": 802,
            "main": "Clouds"
        }
    },
    {
        "day": "04/16",
        "hour": "09",
        "main": {
            "feels_like": 0.88,
            "grnd_level": 941,
            "humidity": 52,
            "pressure": 1019,
            "sea_level": 1019,
            "temp": 4.64,
            "temp_kf": 0,
            "temp_max": 4.64,
            "temp_min": 4.64
        },
        "time": "04/16 09",
        "weather": {
            "description": "雲",
            "icon": "https://openweathermap.org/img/wn/03d@2x.png",
            "id": 802,
            "main": "Clouds"
        }
    },
    {
        "day": "04/16",
        "hour": "12",
        "main": {
            "feels_like": 3.04,
            "grnd_level": 942,
            "humidity": 42,
            "pressure": 1019,
            "sea_level": 1019,
            "temp": 7.43,
            "temp_kf": 0,
            "temp_max": 7.43,
            "temp_min": 7.43
        },
        "time": "04/16 12",
        "weather": {
            "description": "薄い雲",
            "icon": "https://openweathermap.org/img/wn/02d@2x.png",
            "id": 801,
            "main": "Clouds"
        }
    },
    {
        "day": "04/16",
        "hour": "15",
        "main": {
            "feels_like": 2.98,
            "grnd_level": 942,
            "humidity": 43,
            "pressure": 1019,
            "sea_level": 1019,
            "temp": 7.12,
            "temp_kf": 0,
            "temp_max": 7.12,
            "temp_min": 7.12
        },
        "time": "04/16 15",
        "weather": {
            "description": "雲",
            "icon": "https://openweathermap.org/img/wn/03d@2x.png",
            "id": 802,
            "main": "Clouds"
        }
    },
    {
        "day": "04/16",
        "hour": "18",
        "main": {
            "feels_like": -0.2,
            "grnd_level": 942,
            "humidity": 59,
            "pressure": 1021,
            "sea_level": 1021,
            "temp": 2.94,
            "temp_kf": 0,
            "temp_max": 2.94,
            "temp_min": 2.94
        },
        "time": "04/16 18",
        "weather": {
            "description": "曇りがち",
            "icon": "https://openweathermap.org/img/wn/04d@2x.png",
            "id": 803,
            "main": "Clouds"
        }
    },
    {
        "day": "04/16",
        "hour": "21",
        "main": {
            "feels_like": -2.57,
            "grnd_level": 943,
            "humidity": 75,
            "pressure": 1023,
            "sea_level": 1023,
            "temp": 0.14,
            "temp_kf": 0,
            "temp_max": 0.14,
            "temp_min": 0.14
        },
        "time": "04/16 21",
        "weather": {
            "description": "曇りがち",
            "icon": "https://openweathermap.org/img/wn/04n@2x.png",
            "id": 803,
            "main": "Clouds"
        }
    },
    {
        "day": "04/17",
        "hour": "00",
        "main": {
            "feels_like": -3.74,
            "grnd_level": 943,
            "humidity": 76,
            "pressure": 1023,
            "sea_level": 1023,
            "temp": -0.57,
            "temp_kf": 0,
            "temp_max": -0.57,
            "temp_min": -0.57
        },
        "time": "04/17 00",
        "weather": {
            "description": "曇りがち",
            "icon": "https://openweathermap.org/img/wn/04n@2x.png",
            "id": 803,
            "main": "Clouds"
        }
    },
    {
        "day": "04/17",
        "hour": "03",
        "main": {
            "feels_like": -3.59,
            "grnd_level": 944,
            "humidity": 76,
            "pressure": 1023,
            "sea_level": 1023,
            "temp": -0.67,
            "temp_kf": 0,
            "temp_max": -0.67,
            "temp_min": -0.67
        },
        "time": "04/17 03",
        "weather": {
            "description": "曇りがち",
            "icon": "https://openweathermap.org/img/wn/04n@2x.png",
            "id": 803,
            "main": "Clouds"
        }
    },
    {
        "day": "04/17",
        "hour": "06",
        "main": {
            "feels_like": -2.44,
            "grnd_level": 945,
            "humidity": 70,
            "pressure": 1025,
            "sea_level": 1025,
            "temp": 0.42,
            "temp_kf": 0,
            "temp_max": 0.42,
            "temp_min": 0.42
        },
        "time": "04/17 06",
        "weather": {
            "description": "曇りがち",
            "icon": "https://openweathermap.org/img/wn/04d@2x.png",
            "id": 803,
            "main": "Clouds"
        }
    },
    {
        "day": "04/17",
        "hour": "09",
        "main": {
            "feels_like": 5.03,
            "grnd_level": 948,
            "humidity": 43,
            "pressure": 1025,
            "sea_level": 1025,
            "temp": 7.75,
            "temp_kf": 0,
            "temp_max": 7.75,
            "temp_min": 7.75
        },
        "time": "04/17 09",
        "weather": {
            "description": "雲",
            "icon": "https://openweathermap.org/img/wn/03d@2x.png",
            "id": 802,
            "main": "Clouds"
        }
    },
    {
        "day": "04/17",
        "hour": "12",
        "main": {
            "feels_like": 6.77,
            "grnd_level": 947,
            "humidity": 37,
            "pressure": 1024,
            "sea_level": 1024,
            "temp": 9.85,
            "temp_kf": 0,
            "temp_max": 9.85,
            "temp_min": 9.85
        },
        "time": "04/17 12",
        "weather": {
            "description": "晴天",
            "icon": "https://openweathermap.org/img/wn/01d@2x.png",
            "id": 800,
            "main": "Clear"
        }
    },
    {
        "day": "04/17",
        "hour": "15",
        "main": {
            "feels_like": 5.48,
            "grnd_level": 947,
            "humidity": 42,
            "pressure": 1024,
            "sea_level": 1024,
            "temp": 8.88,
            "temp_kf": 0,
            "temp_max": 8.88,
            "temp_min": 8.88
        },
        "time": "04/17 15",
        "weather": {
            "description": "雲",
            "icon": "https://openweathermap.org/img/wn/03d@2x.png",
            "id": 802,
            "main": "Clouds"
        }
    },
    {
        "day": "04/17",
        "hour": "18",
        "main": {
            "feels_like": 0.17,
            "grnd_level": 946,
            "humidity": 67,
            "pressure": 1024,
            "sea_level": 1024,
            "temp": 4.03,
            "temp_kf": 0,
            "temp_max": 4.03,
            "temp_min": 4.03
        },
        "time": "04/17 18",
        "weather": {
            "description": "曇りがち",
            "icon": "https://openweathermap.org/img/wn/04d@2x.png",
            "id": 803,
            "main": "Clouds"
        }
    },
    {
        "day": "04/17",
        "hour": "21",
        "main": {
            "feels_like": -1.38,
            "grnd_level": 946,
            "humidity": 73,
            "pressure": 1025,
            "sea_level": 1025,
            "temp": 2.16,
            "temp_kf": 0,
            "temp_max": 2.16,
            "temp_min": 2.16
        },
        "time": "04/17 21",
        "weather": {
            "description": "厚い雲",
            "icon": "https://openweathermap.org/img/wn/04n@2x.png",
            "id": 804,
            "main": "Clouds"
        }
    },
    {
        "day": "04/18",
        "hour": "00",
        "main": {
            "feels_like": -2.06,
            "grnd_level": 944,
            "humidity": 71,
            "pressure": 1023,
            "sea_level": 1023,
            "temp": 1.19,
            "temp_kf": 0,
            "temp_max": 1.19,
            "temp_min": 1.19
        },
        "time": "04/18 00",
        "weather": {
            "description": "厚い雲",
            "icon": "https://openweathermap.org/img/wn/04n@2x.png",
            "id": 804,
            "main": "Clouds"
        }
    },
    {
        "day": "04/18",
        "hour": "03",
        "main": {
            "feels_like": -0.88,
            "grnd_level": 943,
            "humidity": 72,
            "pressure": 1022,
            "sea_level": 1022,
            "temp": 2.36,
            "temp_kf": 0,
            "temp_max": 2.36,
            "temp_min": 2.36
        },
        "time": "04/18 03",
        "weather": {
            "description": "厚い雲",
            "icon": "https://openweathermap.org/img/wn/04n@2x.png",
            "id": 804,
            "main": "Clouds"
        }
    },
    {
        "day": "04/18",
        "hour": "06",
        "main": {
            "feels_like": -0.12,
            "grnd_level": 943,
            "humidity": 76,
            "pressure": 1022,
            "sea_level": 1022,
            "temp": 3.45,
            "temp_kf": 0,
            "temp_max": 3.45,
            "temp_min": 3.45
        },
        "time": "04/18 06",
        "weather": {
            "description": "厚い雲",
            "icon": "https://openweathermap.org/img/wn/04d@2x.png",
            "id": 804,
            "main": "Clouds"
        }
    },
    {
        "day": "04/18",
        "hour": "09",
        "main": {
            "feels_like": 2.64,
            "grnd_level": 944,
            "humidity": 69,
            "pressure": 1021,
            "sea_level": 1021,
            "temp": 6.5,
            "temp_kf": 0,
            "temp_max": 6.5,
            "temp_min": 6.5
        },
        "time": "04/18 09",
        "weather": {
            "description": "厚い雲",
            "icon": "https://openweathermap.org/img/wn/04d@2x.png",
            "id": 804,
            "main": "Clouds"
        }
    },
    {
        "day": "04/18",
        "hour": "12",
        "main": {
            "feels_like": 2.15,
            "grnd_level": 941,
            "humidity": 71,
            "pressure": 1019,
            "sea_level": 1019,
            "temp": 5.96,
            "temp_kf": 0,
            "temp_max": 5.96,
            "temp_min": 5.96
        },
        "time": "04/18 12",
        "weather": {
            "description": "小雨",
            "icon": "https://openweathermap.org/img/wn/10d@2x.png",
            "id": 500,
            "main": "Rain"
        }
    },
    {
        "day": "04/18",
        "hour": "15",
        "main": {
            "feels_like": 1.27,
            "grnd_level": 940,
            "humidity": 77,
            "pressure": 1018,
            "sea_level": 1018,
            "temp": 4.75,
            "temp_kf": 0,
            "temp_max": 4.75,
            "temp_min": 4.75
        },
        "time": "04/18 15",
        "weather": {
            "description": "小雨",
            "icon": "https://openweathermap.org/img/wn/10d@2x.png",
            "id": 500,
            "main": "Rain"
        }
    },
    {
        "day": "04/18",
        "hour": "18",
        "main": {
            "feels_like": -0.31,
            "grnd_level": 939,
            "humidity": 76,
            "pressure": 1017,
            "sea_level": 1017,
            "temp": 3.64,
            "temp_kf": 0,
            "temp_max": 3.64,
            "temp_min": 3.64
        },
        "time": "04/18 18",
        "weather": {
            "description": "適度な雨",
            "icon": "https://openweathermap.org/img/wn/10d@2x.png",
            "id": 501,
            "main": "Rain"
        }
    },
    {
        "day": "04/18",
        "hour": "21",
        "main": {
            "feels_like": -0.59,
            "grnd_level": 939,
            "humidity": 79,
            "pressure": 1018,
            "sea_level": 1018,
            "temp": 3.84,
            "temp_kf": 0,
            "temp_max": 3.84,
            "temp_min": 3.84
        },
        "time": "04/18 21",
        "weather": {
            "description": "適度な雨",
            "icon": "https://openweathermap.org/img/wn/10n@2x.png",
            "id": 501,
            "main": "Rain"
        }
    },
    {
        "day": "04/19",
        "hour": "00",
        "main": {
            "feels_like": -0.78,
            "grnd_level": 938,
            "humidity": 79,
            "pressure": 1016,
            "sea_level": 1016,
            "temp": 3.83,
            "temp_kf": 0,
            "temp_max": 3.83,
            "temp_min": 3.83
        },
        "time": "04/19 00",
        "weather": {
            "description": "適度な雨",
            "icon": "https://openweathermap.org/img/wn/10n@2x.png",
            "id": 501,
            "main": "Rain"
        }
    },
    {
        "day": "04/19",
        "hour": "03",
        "main": {
            "feels_like": -0.92,
            "grnd_level": 938,
            "humidity": 78,
            "pressure": 1016,
            "sea_level": 1016,
            "temp": 3.48,
            "temp_kf": 0,
            "temp_max": 3.48,
            "temp_min": 3.48
        },
        "time": "04/19 03",
        "weather": {
            "description": "小雨",
            "icon": "https://openweathermap.org/img/wn/10n@2x.png",
            "id": 500,
            "main": "Rain"
        }
    },
    {
        "day": "04/19",
        "hour": "06",
        "main": {
            "feels_like": -1.32,
            "grnd_level": 940,
            "humidity": 78,
            "pressure": 1018,
            "sea_level": 1018,
            "temp": 3.23,
            "temp_kf": 0,
            "temp_max": 3.23,
            "temp_min": 3.23
        },
        "time": "04/19 06",
        "weather": {
            "description": "小雨",
            "icon": "https://openweathermap.org/img/wn/10d@2x.png",
            "id": 500,
            "main": "Rain"
        }
    },
    {
        "day": "04/19",
        "hour": "09",
        "main": {
            "feels_like": -0.7,
            "grnd_level": 941,
            "humidity": 76,
            "pressure": 1019,
            "sea_level": 1019,
            "temp": 3.72,
            "temp_kf": 0,
            "temp_max": 3.72,
            "temp_min": 3.72
        },
        "time": "04/19 09",
        "weather": {
            "description": "小雨",
            "icon": "https://openweathermap.org/img/wn/10d@2x.png",
            "id": 500,
            "main": "Rain"
        }
    },
    {
        "day": "04/19",
        "hour": "12",
        "main": {
            "feels_like": -0.62,
            "grnd_level": 941,
            "humidity": 73,
            "pressure": 1019,
            "sea_level": 1019,
            "temp": 4.11,
            "temp_kf": 0,
            "temp_max": 4.11,
            "temp_min": 4.11
        },
        "time": "04/19 12",
        "weather": {
            "description": "小雨",
            "icon": "https://openweathermap.org/img/wn/10d@2x.png",
            "id": 500,
            "main": "Rain"
        }
    },
    {
        "day": "04/19",
        "hour": "15",
        "main": {
            "feels_like": 0.22,
            "grnd_level": 941,
            "humidity": 73,
            "pressure": 1019,
            "sea_level": 1019,
            "temp": 4.17,
            "temp_kf": 0,
            "temp_max": 4.17,
            "temp_min": 4.17
        },
        "time": "04/19 15",
        "weather": {
            "description": "小雨",
            "icon": "https://openweathermap.org/img/wn/10d@2x.png",
            "id": 500,
            "main": "Rain"
        }
    },
    {
        "day": "04/19",
        "hour": "18",
        "main": {
            "feels_like": 0.27,
            "grnd_level": 941,
            "humidity": 76,
            "pressure": 1019,
            "sea_level": 1019,
            "temp": 3.68,
            "temp_kf": 0,
            "temp_max": 3.68,
            "temp_min": 3.68
        },
        "time": "04/19 18",
        "weather": {
            "description": "小雨",
            "icon": "https://openweathermap.org/img/wn/10d@2x.png",
            "id": 500,
            "main": "Rain"
        }
    },
    {
        "day": "04/19",
        "hour": "21",
        "main": {
            "feels_like": 0.08,
            "grnd_level": 941,
            "humidity": 79,
            "pressure": 1020,
            "sea_level": 1020,
            "temp": 3.17,
            "temp_kf": 0,
            "temp_max": 3.17,
            "temp_min": 3.17
        },
        "time": "04/19 21",
        "weather": {
            "description": "小雨",
            "icon": "https://openweathermap.org/img/wn/10n@2x.png",
            "id": 500,
            "main": "Rain"
        }
    },
    {
        "day": "04/20",
        "hour": "00",
        "main": {
            "feels_like": 0.13,
            "grnd_level": 940,
            "humidity": 79,
            "pressure": 1019,
            "sea_level": 1019,
            "temp": 3.25,
            "temp_kf": 0,
            "temp_max": 3.25,
            "temp_min": 3.25
        },
        "time": "04/20 00",
        "weather": {
            "description": "小雨",
            "icon": "https://openweathermap.org/img/wn/10n@2x.png",
            "id": 500,
            "main": "Rain"
        }
    },
    {
        "day": "04/20",
        "hour": "03",
        "main": {
            "feels_like": 0.02,
            "grnd_level": 938,
            "humidity": 78,
            "pressure": 1016,
            "sea_level": 1016,
            "temp": 3.53,
            "temp_kf": 0,
            "temp_max": 3.53,
            "temp_min": 3.53
        },
        "time": "04/20 03",
        "weather": {
            "description": "小雨",
            "icon": "https://openweathermap.org/img/wn/10n@2x.png",
            "id": 500,
            "main": "Rain"
        }
    }
]