[
    {
        "day": "08/04",
        "hour": "00",
        "main": {
            "feels_like": 28.09,
            "grnd_level": 981,
            "humidity": 89,
            "pressure": 1014,
            "sea_level": 1014,
            "temp": 23.71,
            "temp_kf": 1.86,
            "temp_max": 23.71,
            "temp_min": 21.85
        },
        "time": "08/04 00",
        "weather": {
            "description": "曇りがち",
            "icon": "https://openweathermap.org/img/wn/04n@2x.png",
            "id": 803,
            "main": "Clouds"
        }
    },
    {
        "day": "08/04",
        "hour": "03",
        "main": {
            "feels_like": 25.29,
            "grnd_level": 980,
            "humidity": 92,
            "pressure": 1013,
            "sea_level": 1013,
            "temp": 21.92,
            "temp_kf": 0.98,
            "temp_max": 21.92,
            "temp_min": 20.94
        },
        "time": "08/04 03",
        "weather": {
            "description": "曇りがち",
            "icon": "https://openweathermap.org/img/wn/04n@2x.png",
            "id": 803,
            "main": "Clouds"
        }
    },
    {
        "day": "08/04",
        "hour": "06",
        "main": {
            "feels_like": 24.8,
            "grnd_level": 982,
            "humidity": 93,
            "pressure": 1015,
            "sea_level": 1015,
            "temp": 21.43,
            "temp_kf": 0.28,
            "temp_max": 21.43,
            "temp_min": 21.15
        },
        "time": "08/04 06",
        "weather": {
            "description": "雲",
            "icon": "https://openweathermap.org/img/wn/03d@2x.png",
            "id": 802,
            "main": "Clouds"
        }
    },
    {
        "day": "08/04",
        "hour": "09",
        "main": {
            "feels_like": 31.02,
            "grnd_level": 983,
            "humidity": 69,
            "pressure": 1015,
            "sea_level": 1015,
            "temp": 27.37,
            "temp_kf": -0.02,
            "temp_max": 27.39,
            "temp_min": 27.37
        },
        "time": "08/04 09",
        "weather": {
            "description": "曇りがち",
            "icon": "https://openweathermap.org/img/wn/04d@2x.png",
            "id": 803,
            "main": "Clouds"
        }
    },
    {
        "day": "08/04",
        "hour": "12",
        "main": {
            "feels_like": 35.39,
            "grnd_level": 983,
            "humidity": 50,
            "pressure": 1015,
            "sea_level": 1015,
            "temp": 32.25,
            "temp_kf": 0,
            "temp_max": 32.25,
            "temp_min": 32.25
        },
        "time": "08/04 12",
        "weather": {
            "description": "厚い雲",
            "icon": "https://openweathermap.org/img/wn/04d@2x.png",
            "id": 804,
            "main": "Clouds"
        }
    },
    {
        "day": "08/04",
        "hour": "15",
        "main": {
            "feels_like": 34.27,
            "grnd_level": 982,
            "humidity": 43,
            "pressure": 1014,
            "sea_level": 1014,
            "temp": 32.53,
            "temp_kf": 0,
            "temp_max": 32.53,
            "temp_min": 32.53
        },
        "time": "08/04 15",
        "weather": {
            "description": "厚い雲",
            "icon": "https://openweathermap.org/img/wn/04d@2x.png",
            "id": 804,
            "main": "Clouds"
        }
    },
    {
        "day": "08/04",
        "hour": "18",
        "main": {
            "feels_like": 31.82,
            "grnd_level": 982,
            "humidity": 67,
            "pressure": 1014,
            "sea_level": 1014,
            "temp": 28.28,
            "temp_kf": 0,
            "temp_max": 28.28,
            "temp_min": 28.28
        },
        "time": "08/04 18",
        "weather": {
            "description": "厚い雲",
            "icon": "https://openweathermap.org/img/wn/04d@2x.png",
            "id": 804,
            "main": "Clouds"
        }
    },
    {
        "day": "08/04",
        "hour": "21",
        "main": {
            "feels_like": 26.67,
            "grnd_level": 982,
            "humidity": 81,
            "pressure": 1015,
            "sea_level": 1015,
            "temp": 23.38,
            "temp_kf": 0,
            "temp_max": 23.38,
            "temp_min": 23.38
        },
        "time": "08/04 21",
        "weather": {
            "description": "厚い雲",
            "icon": "https://openweathermap.org/img/wn/04n@2x.png",
            "id": 804,
            "main": "Clouds"
        }
    },
    {
        "day": "08/05",
        "hour": "00",
        "main": {
            "feels_like": 25.53,
            "grnd_level": 982,
            "humidity": 86,
            "pressure": 1015,
            "sea_level": 1015,
            "temp": 22.16,
            "temp_kf": 0,
            "temp_max": 22.16,
            "temp_min": 22.16
        },
        "time": "08/05 00",
        "weather": {
            "description": "厚い雲",
            "icon": "https://openweathermap.org/img/wn/04n@2x.png",
            "id": 804,
            "main": "Clouds"
        }
    },
    {
        "day": "08/05",
        "hour": "03",
        "main": {
            "feels_like": 24.33,
            "grnd_level": 983,
            "humidity": 88,
            "pressure": 1016,
            "sea_level": 1016,
            "temp": 21.59,
            "temp_kf": 0,
            "temp_max": 21.59,
            "temp_min": 21.59
        },
        "time": "08/05 03",
        "weather": {
            "description": "厚い雲",
            "icon": "https://openweathermap.org/img/wn/04n@2x.png",
            "id": 804,
            "main": "Clouds"
        }
    },
    {
        "day": "08/05",
        "hour": "06",
        "main": {
            "feels_like": 25.66,
            "grnd_level": 984,
            "humidity": 88,
            "pressure": 1017,
            "sea_level": 1017,
            "temp": 22.19,
            "temp_kf": 0,
            "temp_max": 22.19,
            "temp_min": 22.19
        },
        "time": "08/05 06",
        "weather": {
            "description": "厚い雲",
            "icon": "https://openweathermap.org/img/wn/04d@2x.png",
            "id": 804,
            "main": "Clouds"
        }
    },
    {
        "day": "08/05",
        "hour": "09",
        "main": {
            "feels_like": 32.33,
            "grnd_level": 985,
            "humidity": 66,
            "pressure": 1017,
            "sea_level": 1017,
            "temp": 28.2,
            "temp_kf": 0,
            "temp_max": 28.2,
            "temp_min": 28.2
        },
        "time": "08/05 09",
        "weather": {
            "description": "厚い雲",
            "icon": "https://openweathermap.org/img/wn/04d@2x.png",
            "id": 804,
            "main": "Clouds"
        }
    },
    {
        "day": "08/05",
        "hour": "12",
        "main": {
            "feels_like": 36.5,
            "grnd_level": 985,
            "humidity": 51,
            "pressure": 1017,
            "sea_level": 1017,
            "temp": 32.87,
            "temp_kf": 0,
            "temp_max": 32.87,
            "temp_min": 32.87
        },
        "time": "08/05 12",
        "weather": {
            "description": "厚い雲",
            "icon": "https://openweathermap.org/img/wn/04d@2x.png",
            "id": 804,
            "main": "Clouds"
        }
    },
    {
        "day": "08/05",
        "hour": "15",
        "main": {
            "feels_like": 35.92,
            "grnd_level": 983,
            "humidity": 47,
            "pressure": 1015,
            "sea_level": 1015,
            "temp": 33.15,
            "temp_kf": 0,
            "temp_max": 33.15,
            "temp_min": 33.15
        },
        "time": "08/05 15",
        "weather": {
            "description": "厚い雲",
            "icon": "https://openweathermap.org/img/wn/04d@2x.png",
            "id": 804,
            "main": "Clouds"
        }
    },
    {
        "day": "08/05",
        "hour": "18",
        "main": {
            "feels_like": 32.28,
            "grnd_level": 983,
            "humidity": 67,
            "pressure": 1015,
            "sea_level": 1015,
            "temp": 28.87,
            "temp_kf": 0,
            "temp_max": 28.87,
            "temp_min": 28.87
        },
        "time": "08/05 18",
        "weather": {
            "description": "厚い雲",
            "icon": "https://openweathermap.org/img/wn/04d@2x.png",
            "id": 804,
            "main": "Clouds"
        }
    },
    {
        "day": "08/05",
        "hour": "21",
        "main": {
            "feels_like": 27.56,
            "grnd_level": 983,
            "humidity": 79,
            "pressure": 1016,
            "sea_level": 1016,
            "temp": 24.04,
            "temp_kf": 0,
            "temp_max": 24.04,
            "temp_min": 24.04
        },
        "time": "08/05 21",
        "weather": {
            "description": "厚い雲",
            "icon": "https://openweathermap.org/img/wn/04n@2x.png",
            "id": 804,
            "main": "Clouds"
        }
    },
    {
        "day": "08/06",
        "hour": "00",
        "main": {
            "feels_like": 26.04,
            "grnd_level": 982,
            "humidity": 83,
            "pressure": 1015,
            "sea_level": 1015,
            "temp": 22.71,
            "temp_kf": 0,
            "temp_max": 22.71,
            "temp_min": 22.71
        },
        "time": "08/06 00",
        "weather": {
            "description": "厚い雲",
            "icon": "https://openweathermap.org/img/wn/04n@2x.png",
            "id": 804,
            "main": "Clouds"
        }
    },
    {
        "day": "08/06",
        "hour": "03",
        "main": {
            "feels_like": 24.66,
            "grnd_level": 981,
            "humidity": 87,
            "pressure": 1014,
            "sea_level": 1014,
            "temp": 21.58,
            "temp_kf": 0,
            "temp_max": 21.58,
            "temp_min": 21.58
        },
        "time": "08/06 03",
        "weather": {
            "description": "厚い雲",
            "icon": "https://openweathermap.org/img/wn/04n@2x.png",
            "id": 804,
            "main": "Clouds"
        }
    },
    {
        "day": "08/06",
        "hour": "06",
        "main": {
            "feels_like": 24.93,
            "grnd_level": 981,
            "humidity": 90,
            "pressure": 1014,
            "sea_level": 1014,
            "temp": 21.61,
            "temp_kf": 0,
            "temp_max": 21.61,
            "temp_min": 21.61
        },
        "time": "08/06 06",
        "weather": {
            "description": "曇りがち",
            "icon": "https://openweathermap.org/img/wn/04d@2x.png",
            "id": 803,
            "main": "Clouds"
        }
    },
    {
        "day": "08/06",
        "hour": "09",
        "main": {
            "feels_like": 31.04,
            "grnd_level": 982,
            "humidity": 71,
            "pressure": 1014,
            "sea_level": 1014,
            "temp": 27.48,
            "temp_kf": 0,
            "temp_max": 27.48,
            "temp_min": 27.48
        },
        "time": "08/06 09",
        "weather": {
            "description": "曇りがち",
            "icon": "https://openweathermap.org/img/wn/04d@2x.png",
            "id": 803,
            "main": "Clouds"
        }
    },
    {
        "day": "08/06",
        "hour": "12",
        "main": {
            "feels_like": 32.71,
            "grnd_level": 982,
            "humidity": 49,
            "pressure": 1013,
            "sea_level": 1013,
            "temp": 31.38,
            "temp_kf": 0,
            "temp_max": 31.38,
            "temp_min": 31.38
        },
        "time": "08/06 12",
        "weather": {
            "description": "厚い雲",
            "icon": "https://openweathermap.org/img/wn/04d@2x.png",
            "id": 804,
            "main": "Clouds"
        }
    },
    {
        "day": "08/06",
        "hour": "15",
        "main": {
            "feels_like": 31.92,
            "grnd_level": 980,
            "humidity": 48,
            "pressure": 1012,
            "sea_level": 1012,
            "temp": 31.61,
            "temp_kf": 0,
            "temp_max": 31.61,
            "temp_min": 31.61
        },
        "time": "08/06 15",
        "weather": {
            "description": "厚い雲",
            "icon": "https://openweathermap.org/img/wn/04d@2x.png",
            "id": 804,
            "main": "Clouds"
        }
    },
    {
        "day": "08/06",
        "hour": "18",
        "main": {
            "feels_like": 31.5,
            "grnd_level": 980,
            "humidity": 66,
            "pressure": 1012,
            "sea_level": 1012,
            "temp": 28.33,
            "temp_kf": 0,
            "temp_max": 28.33,
            "temp_min": 28.33
        },
        "time": "08/06 18",
        "weather": {
            "description": "曇りがち",
            "icon": "https://openweathermap.org/img/wn/04d@2x.png",
            "id": 803,
            "main": "Clouds"
        }
    },
    {
        "day": "08/06",
        "hour": "21",
        "main": {
            "feels_like": 26.91,
            "grnd_level": 980,
            "humidity": 82,
            "pressure": 1012,
            "sea_level": 1012,
            "temp": 23.48,
            "temp_kf": 0,
            "temp_max": 23.48,
            "temp_min": 23.48
        },
        "time": "08/06 21",
        "weather": {
            "description": "曇りがち",
            "icon": "https://openweathermap.org/img/wn/04n@2x.png",
            "id": 803,
            "main": "Clouds"
        }
    },
    {
        "day": "08/07",
        "hour": "00",
        "main": {
            "feels_like": 26.2,
            "grnd_level": 979,
            "humidity": 89,
            "pressure": 1012,
            "sea_level": 1012,
            "temp": 22.49,
            "temp_kf": 0,
            "temp_max": 22.49,
            "temp_min": 22.49
        },
        "time": "08/07 00",
        "weather": {
            "description": "厚い雲",
            "icon": "https://openweathermap.org/img/wn/04n@2x.png",
            "id": 804,
            "main": "Clouds"
        }
    },
    {
        "day": "08/07",
        "hour": "03",
        "main": {
            "feels_like": 25.8,
            "grnd_level": 978,
            "humidity": 91,
            "pressure": 1010,
            "sea_level": 1010,
            "temp": 22.06,
            "temp_kf": 0,
            "temp_max": 22.06,
            "temp_min": 22.06
        },
        "time": "08/07 03",
        "weather": {
            "description": "厚い雲",
            "icon": "https://openweathermap.org/img/wn/04n@2x.png",
            "id": 804,
            "main": "Clouds"
        }
    },
    {
        "day": "08/07",
        "hour": "06",
        "main": {
            "feels_like": 26.62,
            "grnd_level": 978,
            "humidity": 91,
            "pressure": 1010,
            "sea_level": 1010,
            "temp": 22.67,
            "temp_kf": 0,
            "temp_max": 22.67,
            "temp_min": 22.67
        },
        "time": "08/07 06",
        "weather": {
            "description": "厚い雲",
            "icon": "https://openweathermap.org/img/wn/04d@2x.png",
            "id": 804,
            "main": "Clouds"
        }
    },
    {
        "day": "08/07",
        "hour": "09",
        "main": {
            "feels_like": 30.49,
            "grnd_level": 978,
            "humidity": 77,
            "pressure": 1010,
            "sea_level": 1010,
            "temp": 27.11,
            "temp_kf": 0,
            "temp_max": 27.11,
            "temp_min": 27.11
        },
        "time": "08/07 09",
        "weather": {
            "description": "小雨",
            "icon": "https://openweathermap.org/img/wn/10d@2x.png",
            "id": 500,
            "main": "Rain"
        }
    },
    {
        "day": "08/07",
        "hour": "12",
        "main": {
            "feels_like": 29.91,
            "grnd_level": 977,
            "humidity": 74,
            "pressure": 1009,
            "sea_level": 1009,
            "temp": 27.47,
            "temp_kf": 0,
            "temp_max": 27.47,
            "temp_min": 27.47
        },
        "time": "08/07 12",
        "weather": {
            "description": "小雨",
            "icon": "https://openweathermap.org/img/wn/10d@2x.png",
            "id": 500,
            "main": "Rain"
        }
    },
    {
        "day": "08/07",
        "hour": "15",
        "main": {
            "feels_like": 26.3,
            "grnd_level": 976,
            "humidity": 80,
            "pressure": 1009,
            "sea_level": 1009,
            "temp": 24.4,
            "temp_kf": 0,
            "temp_max": 24.4,
            "temp_min": 24.4
        },
        "time": "08/07 15",
        "weather": {
            "description": "小雨",
            "icon": "https://openweathermap.org/img/wn/10d@2x.png",
            "id": 500,
            "main": "Rain"
        }
    },
    {
        "day": "08/07",
        "hour": "18",
        "main": {
            "feels_like": 26.48,
            "grnd_level": 976,
            "humidity": 77,
            "pressure": 1008,
            "sea_level": 1008,
            "temp": 24.52,
            "temp_kf": 0,
            "temp_max": 24.52,
            "temp_min": 24.52
        },
        "time": "08/07 18",
        "weather": {
            "description": "厚い雲",
            "icon": "https://openweathermap.org/img/wn/04d@2x.png",
            "id": 804,
            "main": "Clouds"
        }
    },
    {
        "day": "08/07",
        "hour": "21",
        "main": {
            "feels_like": 24.93,
            "grnd_level": 977,
            "humidity": 82,
            "pressure": 1009,
            "sea_level": 1009,
            "temp": 22.72,
            "temp_kf": 0,
            "temp_max": 22.72,
            "temp_min": 22.72
        },
        "time": "08/07 21",
        "weather": {
            "description": "厚い雲",
            "icon": "https://openweathermap.org/img/wn/04n@2x.png",
            "id": 804,
            "main": "Clouds"
        }
    },
    {
        "day": "08/08",
        "hour": "00",
        "main": {
            "feels_like": 25.42,
            "grnd_level": 976,
            "humidity": 80,
            "pressure": 1009,
            "sea_level": 1009,
            "temp": 22.74,
            "temp_kf": 0,
            "temp_max": 22.74,
            "temp_min": 22.74
        },
        "time": "08/08 00",
        "weather": {
            "description": "厚い雲",
            "icon": "https://openweathermap.org/img/wn/04n@2x.png",
            "id": 804,
            "main": "Clouds"
        }
    },
    {
        "day": "08/08",
        "hour": "03",
        "main": {
            "feels_like": 24.71,
            "grnd_level": 975,
            "humidity": 85,
            "pressure": 1007,
            "sea_level": 1007,
            "temp": 21.81,
            "temp_kf": 0,
            "temp_max": 21.81,
            "temp_min": 21.81
        },
        "time": "08/08 03",
        "weather": {
            "description": "厚い雲",
            "icon": "https://openweathermap.org/img/wn/04n@2x.png",
            "id": 804,
            "main": "Clouds"
        }
    },
    {
        "day": "08/08",
        "hour": "06",
        "main": {
            "feels_like": 25.47,
            "grnd_level": 974,
            "humidity": 90,
            "pressure": 1007,
            "sea_level": 1007,
            "temp": 21.91,
            "temp_kf": 0,
            "temp_max": 21.91,
            "temp_min": 21.91
        },
        "time": "08/08 06",
        "weather": {
            "description": "小雨",
            "icon": "https://openweathermap.org/img/wn/10d@2x.png",
            "id": 500,
            "main": "Rain"
        }
    },
    {
        "day": "08/08",
        "hour": "09",
        "main": {
            "feels_like": 27.64,
            "grnd_level": 974,
            "humidity": 87,
            "pressure": 1006,
            "sea_level": 1006,
            "temp": 24.05,
            "temp_kf": 0,
            "temp_max": 24.05,
            "temp_min": 24.05
        },
        "time": "08/08 09",
        "weather": {
            "description": "小雨",
            "icon": "https://openweathermap.org/img/wn/10d@2x.png",
            "id": 500,
            "main": "Rain"
        }
    },
    {
        "day": "08/08",
        "hour": "12",
        "main": {
            "feels_like": 27.11,
            "grnd_level": 974,
            "humidity": 85,
            "pressure": 1006,
            "sea_level": 1006,
            "temp": 24.5,
            "temp_kf": 0,
            "temp_max": 24.5,
            "temp_min": 24.5
        },
        "time": "08/08 12",
        "weather": {
            "description": "小雨",
            "icon": "https://openweathermap.org/img/wn/10d@2x.png",
            "id": 500,
            "main": "Rain"
        }
    },
    {
        "day": "08/08",
        "hour": "15",
        "main": {
            "feels_like": 25.58,
            "grnd_level": 973,
            "humidity": 91,
            "pressure": 1006,
            "sea_level": 1006,
            "temp": 23.04,
            "temp_kf": 0,
            "temp_max": 23.04,
            "temp_min": 23.04
        },
        "time": "08/08 15",
        "weather": {
            "description": "小雨",
            "icon": "https://openweathermap.org/img/wn/10d@2x.png",
            "id": 500,
            "main": "Rain"
        }
    },
    {
        "day": "08/08",
        "hour": "18",
        "main": {
            "feels_like": 25.52,
            "grnd_level": 973,
            "humidity": 92,
            "pressure": 1005,
            "sea_level": 1005,
            "temp": 22.8,
            "temp_kf": 0,
            "temp_max": 22.8,
            "temp_min": 22.8
        },
        "time": "08/08 18",
        "weather": {
            "description": "小雨",
            "icon": "https://openweathermap.org/img/wn/10d@2x.png",
            "id": 500,
            "main": "Rain"
        }
    },
    {
        "day": "08/08",
        "hour": "21",
        "main": {
            "feels_like": 25.11,
            "grnd_level": 974,
            "humidity": 95,
            "pressure": 1007,
            "sea_level": 1007,
            "temp": 22.38,
            "temp_kf": 0,
            "temp_max": 22.38,
            "temp_min": 22.38
        },
        "time": "08/08 21",
        "weather": {
            "description": "小雨",
            "icon": "https://openweathermap.org/img/wn/10n@2x.png",
            "id": 500,
            "main": "Rain"
        }
    }
]