[
    {
        "day": "07/12",
        "hour": "09",
        "main": {
            "feels_like": 23.22,
            "grnd_level": 999,
            "humidity": 82,
            "pressure": 1006,
            "sea_level": 1008,
            "temp": 22.01,
            "temp_kf": 0.62,
            "temp_max": 22.01,
            "temp_min": 21.39
        },
        "time": "07/12 09",
        "weather": {
            "description": "小雨",
            "icon": "https://openweathermap.org/img/wn/10d@2x.png",
            "id": 500,
            "main": "Rain"
        }
    },
    {
        "day": "07/12",
        "hour": "12",
        "main": {
            "feels_like": 23.52,
            "grnd_level": 999,
            "humidity": 80,
            "pressure": 1008,
            "sea_level": 1009,
            "temp": 21.64,
            "temp_kf": 0.27,
            "temp_max": 21.64,
            "temp_min": 21.37
        },
        "time": "07/12 12",
        "weather": {
            "description": "小雨",
            "icon": "https://openweathermap.org/img/wn/10d@2x.png",
            "id": 500,
            "main": "Rain"
        }
    },
    {
        "day": "07/12",
        "hour": "15",
        "main": {
            "feels_like": 23.96,
            "grnd_level": 998,
            "humidity": 78,
            "pressure": 1008,
            "sea_level": 1008,
            "temp": 22.13,
            "temp_kf": 0.03,
            "temp_max": 22.13,
            "temp_min": 22.1
        },
        "time": "07/12 15",
        "weather": {
            "description": "小雨",
            "icon": "https://openweathermap.org/img/wn/10d@2x.png",
            "id": 500,
            "main": "Rain"
        }
    },
    {
        "day": "07/12",
        "hour": "18",
        "main": {
            "feels_like": 22.2,
            "grnd_level": 999,
            "humidity": 76,
            "pressure": 1009,
            "sea_level": 1009,
            "temp": 21.5,
            "temp_kf": 0.01,
            "temp_max": 21.5,
            "temp_min": 21.49
        },
        "time": "07/12 18",
        "weather": {
            "description": "小雨",
            "icon": "https://openweathermap.org/img/wn/10d@2x.png",
            "id": 500,
            "main": "Rain"
        }
    },
    {
        "day": "07/12",
        "hour": "21",
        "main": {
            "feels_like": 21.42,
            "grnd_level": 1001,
            "humidity": 79,
            "pressure": 1010,
            "sea_level": 1010,
            "temp": 20.58,
            "temp_kf": 0,
            "temp_max": 20.58,
            "temp_min": 20.58
        },
        "time": "07/12 21",
        "weather": {
            "description": "小雨",
            "icon": "https://openweathermap.org/img/wn/10n@2x.png",
            "id": 500,
            "main": "Rain"
        }
    },
    {
        "day": "07/13",
        "hour": "00",
        "main": {
            "feels_like": 21.66,
            "grnd_level": 1000,
            "humidity": 79,
            "pressure": 1009,
            "sea_level": 1009,
            "temp": 20.12,
            "temp_kf": 0,
            "temp_max": 20.12,
            "temp_min": 20.12
        },
        "time": "07/13 00",
        "weather": {
            "description": "小雨",
            "icon": "https://openweathermap.org/img/wn/10n@2x.png",
            "id": 500,
            "main": "Rain"
        }
    },
    {
        "day": "07/13",
        "hour": "03",
        "main": {
            "feels_like": 21.6,
            "grnd_level": 1000,
            "humidity": 79,
            "pressure": 1009,
            "sea_level": 1009,
            "temp": 19.77,
            "temp_kf": 0,
            "temp_max": 19.77,
            "temp_min": 19.77
        },
        "time": "07/13 03",
        "weather": {
            "description": "小雨",
            "icon": "https://openweathermap.org/img/wn/10n@2x.png",
            "id": 500,
            "main": "Rain"
        }
    },
    {
        "day": "07/13",
        "hour": "06",
        "main": {
            "feels_like": 21.32,
            "grnd_level": 1001,
            "humidity": 78,
            "pressure": 1010,
            "sea_level": 1010,
            "temp": 20.03,
            "temp_kf": 0,
            "temp_max": 20.03,
            "temp_min": 20.03
        },
        "time": "07/13 06",
        "weather": {
            "description": "小雨",
            "icon": "https://openweathermap.org/img/wn/10d@2x.png",
            "id": 500,
            "main": "Rain"
        }
    },
    {
        "day": "07/13",
        "hour": "09",
        "main": {
            "feels_like": 25.36,
            "grnd_level": 1001,
            "humidity": 63,
            "pressure": 1010,
            "sea_level": 1010,
            "temp": 23.79,
            "temp_kf": 0,
            "temp_max": 23.79,
            "temp_min": 23.79
        },
        "time": "07/13 09",
        "weather": {
            "description": "小雨",
            "icon": "https://openweathermap.org/img/wn/10d@2x.png",
            "id": 500,
            "main": "Rain"
        }
    },
    {
        "day": "07/13",
        "hour": "12",
        "main": {
            "feels_like": 27.25,
            "grnd_level": 1000,
            "humidity": 52,
            "pressure": 1009,
            "sea_level": 1009,
            "temp": 26.63,
            "temp_kf": 0,
            "temp_max": 26.63,
            "temp_min": 26.63
        },
        "time": "07/13 12",
        "weather": {
            "description": "厚い雲",
            "icon": "https://openweathermap.org/img/wn/04d@2x.png",
            "id": 804,
            "main": "Clouds"
        }
    },
    {
        "day": "07/13",
        "hour": "15",
        "main": {
            "feels_like": 25.76,
            "grnd_level": 999,
            "humidity": 56,
            "pressure": 1008,
            "sea_level": 1008,
            "temp": 25.67,
            "temp_kf": 0,
            "temp_max": 25.67,
            "temp_min": 25.67
        },
        "time": "07/13 15",
        "weather": {
            "description": "厚い雲",
            "icon": "https://openweathermap.org/img/wn/04d@2x.png",
            "id": 804,
            "main": "Clouds"
        }
    },
    {
        "day": "07/13",
        "hour": "18",
        "main": {
            "feels_like": 23.55,
            "grnd_level": 998,
            "humidity": 70,
            "pressure": 1008,
            "sea_level": 1008,
            "temp": 22.65,
            "temp_kf": 0,
            "temp_max": 22.65,
            "temp_min": 22.65
        },
        "time": "07/13 18",
        "weather": {
            "description": "厚い雲",
            "icon": "https://openweathermap.org/img/wn/04d@2x.png",
            "id": 804,
            "main": "Clouds"
        }
    },
    {
        "day": "07/13",
        "hour": "21",
        "main": {
            "feels_like": 22.78,
            "grnd_level": 998,
            "humidity": 72,
            "pressure": 1007,
            "sea_level": 1007,
            "temp": 21.7,
            "temp_kf": 0,
            "temp_max": 21.7,
            "temp_min": 21.7
        },
        "time": "07/13 21",
        "weather": {
            "description": "厚い雲",
            "icon": "https://openweathermap.org/img/wn/04n@2x.png",
            "id": 804,
            "main": "Clouds"
        }
    },
    {
        "day": "07/14",
        "hour": "00",
        "main": {
            "feels_like": 23.18,
            "grnd_level": 996,
            "humidity": 74,
            "pressure": 1005,
            "sea_level": 1005,
            "temp": 21.68,
            "temp_kf": 0,
            "temp_max": 21.68,
            "temp_min": 21.68
        },
        "time": "07/14 00",
        "weather": {
            "description": "小雨",
            "icon": "https://openweathermap.org/img/wn/10n@2x.png",
            "id": 500,
            "main": "Rain"
        }
    },
    {
        "day": "07/14",
        "hour": "03",
        "main": {
            "feels_like": 23.39,
            "grnd_level": 993,
            "humidity": 80,
            "pressure": 1003,
            "sea_level": 1003,
            "temp": 21.04,
            "temp_kf": 0,
            "temp_max": 21.04,
            "temp_min": 21.04
        },
        "time": "07/14 03",
        "weather": {
            "description": "小雨",
            "icon": "https://openweathermap.org/img/wn/10n@2x.png",
            "id": 500,
            "main": "Rain"
        }
    },
    {
        "day": "07/14",
        "hour": "06",
        "main": {
            "feels_like": 23.15,
            "grnd_level": 993,
            "humidity": 84,
            "pressure": 1002,
            "sea_level": 1002,
            "temp": 20.61,
            "temp_kf": 0,
            "temp_max": 20.61,
            "temp_min": 20.61
        },
        "time": "07/14 06",
        "weather": {
            "description": "小雨",
            "icon": "https://openweathermap.org/img/wn/10d@2x.png",
            "id": 500,
            "main": "Rain"
        }
    },
    {
        "day": "07/14",
        "hour": "09",
        "main": {
            "feels_like": 23.22,
            "grnd_level": 993,
            "humidity": 86,
            "pressure": 1002,
            "sea_level": 1002,
            "temp": 20.82,
            "temp_kf": 0,
            "temp_max": 20.82,
            "temp_min": 20.82
        },
        "time": "07/14 09",
        "weather": {
            "description": "適度な雨",
            "icon": "https://openweathermap.org/img/wn/10d@2x.png",
            "id": 501,
            "main": "Rain"
        }
    },
    {
        "day": "07/14",
        "hour": "12",
        "main": {
            "feels_like": 22.81,
            "grnd_level": 993,
            "humidity": 87,
            "pressure": 1002,
            "sea_level": 1002,
            "temp": 20.79,
            "temp_kf": 0,
            "temp_max": 20.79,
            "temp_min": 20.79
        },
        "time": "07/14 12",
        "weather": {
            "description": "適度な雨",
            "icon": "https://openweathermap.org/img/wn/10d@2x.png",
            "id": 501,
            "main": "Rain"
        }
    },
    {
        "day": "07/14",
        "hour": "15",
        "main": {
            "feels_like": 23.36,
            "grnd_level": 992,
            "humidity": 88,
            "pressure": 1001,
            "sea_level": 1001,
            "temp": 20.85,
            "temp_kf": 0,
            "temp_max": 20.85,
            "temp_min": 20.85
        },
        "time": "07/14 15",
        "weather": {
            "description": "適度な雨",
            "icon": "https://openweathermap.org/img/wn/10d@2x.png",
            "id": 501,
            "main": "Rain"
        }
    },
    {
        "day": "07/14",
        "hour": "18",
        "main": {
            "feels_like": 22.67,
            "grnd_level": 992,
            "humidity": 87,
            "pressure": 1002,
            "sea_level": 1002,
            "temp": 20.75,
            "temp_kf": 0,
            "temp_max": 20.75,
            "temp_min": 20.75
        },
        "time": "07/14 18",
        "weather": {
            "description": "適度な雨",
            "icon": "https://openweathermap.org/img/wn/10d@2x.png",
            "id": 501,
            "main": "Rain"
        }
    },
    {
        "day": "07/14",
        "hour": "21",
        "main": {
            "feels_like": 23.26,
            "grnd_level": 994,
            "humidity": 86,
            "pressure": 1003,
            "sea_level": 1003,
            "temp": 20.83,
            "temp_kf": 0,
            "temp_max": 20.83,
            "temp_min": 20.83
        },
        "time": "07/14 21",
        "weather": {
            "description": "小雨",
            "icon": "https://openweathermap.org/img/wn/10n@2x.png",
            "id": 500,
            "main": "Rain"
        }
    },
    {
        "day": "07/15",
        "hour": "00",
        "main": {
            "feels_like": 23.34,
            "grnd_level": 994,
            "humidity": 86,
            "pressure": 1003,
            "sea_level": 1003,
            "temp": 20.86,
            "temp_kf": 0,
            "temp_max": 20.86,
            "temp_min": 20.86
        },
        "time": "07/15 00",
        "weather": {
            "description": "小雨",
            "icon": "https://openweathermap.org/img/wn/10n@2x.png",
            "id": 500,
            "main": "Rain"
        }
    },
    {
        "day": "07/15",
        "hour": "03",
        "main": {
            "feels_like": 23,
            "grnd_level": 994,
            "humidity": 86,
            "pressure": 1003,
            "sea_level": 1003,
            "temp": 20.8,
            "temp_kf": 0,
            "temp_max": 20.8,
            "temp_min": 20.8
        },
        "time": "07/15 03",
        "weather": {
            "description": "小雨",
            "icon": "https://openweathermap.org/img/wn/10n@2x.png",
            "id": 500,
            "main": "Rain"
        }
    },
    {
        "day": "07/15",
        "hour": "06",
        "main": {
            "feels_like": 22.68,
            "grnd_level": 994,
            "humidity": 85,
            "pressure": 1004,
            "sea_level": 1004,
            "temp": 20.77,
            "temp_kf": 0,
            "temp_max": 20.77,
            "temp_min": 20.77
        },
        "time": "07/15 06",
        "weather": {
            "description": "小雨",
            "icon": "https://openweathermap.org/img/wn/10d@2x.png",
            "id": 500,
            "main": "Rain"
        }
    },
    {
        "day": "07/15",
        "hour": "09",
        "main": {
            "feels_like": 23.68,
            "grnd_level": 995,
            "humidity": 83,
            "pressure": 1005,
            "sea_level": 1005,
            "temp": 21.36,
            "temp_kf": 0,
            "temp_max": 21.36,
            "temp_min": 21.36
        },
        "time": "07/15 09",
        "weather": {
            "description": "小雨",
            "icon": "https://openweathermap.org/img/wn/10d@2x.png",
            "id": 500,
            "main": "Rain"
        }
    },
    {
        "day": "07/15",
        "hour": "12",
        "main": {
            "feels_like": 24.74,
            "grnd_level": 995,
            "humidity": 79,
            "pressure": 1005,
            "sea_level": 1005,
            "temp": 22.17,
            "temp_kf": 0,
            "temp_max": 22.17,
            "temp_min": 22.17
        },
        "time": "07/15 12",
        "weather": {
            "description": "小雨",
            "icon": "https://openweathermap.org/img/wn/10d@2x.png",
            "id": 500,
            "main": "Rain"
        }
    },
    {
        "day": "07/15",
        "hour": "15",
        "main": {
            "feels_like": 27.95,
            "grnd_level": 995,
            "humidity": 67,
            "pressure": 1004,
            "sea_level": 1004,
            "temp": 25.27,
            "temp_kf": 0,
            "temp_max": 25.27,
            "temp_min": 25.27
        },
        "time": "07/15 15",
        "weather": {
            "description": "小雨",
            "icon": "https://openweathermap.org/img/wn/10d@2x.png",
            "id": 500,
            "main": "Rain"
        }
    },
    {
        "day": "07/15",
        "hour": "18",
        "main": {
            "feels_like": 25.58,
            "grnd_level": 996,
            "humidity": 77,
            "pressure": 1005,
            "sea_level": 1005,
            "temp": 23.18,
            "temp_kf": 0,
            "temp_max": 23.18,
            "temp_min": 23.18
        },
        "time": "07/15 18",
        "weather": {
            "description": "小雨",
            "icon": "https://openweathermap.org/img/wn/10d@2x.png",
            "id": 500,
            "main": "Rain"
        }
    },
    {
        "day": "07/15",
        "hour": "21",
        "main": {
            "feels_like": 25.02,
            "grnd_level": 997,
            "humidity": 80,
            "pressure": 1006,
            "sea_level": 1006,
            "temp": 22.24,
            "temp_kf": 0,
            "temp_max": 22.24,
            "temp_min": 22.24
        },
        "time": "07/15 21",
        "weather": {
            "description": "小雨",
            "icon": "https://openweathermap.org/img/wn/10n@2x.png",
            "id": 500,
            "main": "Rain"
        }
    },
    {
        "day": "07/16",
        "hour": "00",
        "main": {
            "feels_like": 24.25,
            "grnd_level": 997,
            "humidity": 82,
            "pressure": 1007,
            "sea_level": 1007,
            "temp": 21.77,
            "temp_kf": 0,
            "temp_max": 21.77,
            "temp_min": 21.77
        },
        "time": "07/16 00",
        "weather": {
            "description": "小雨",
            "icon": "https://openweathermap.org/img/wn/10n@2x.png",
            "id": 500,
            "main": "Rain"
        }
    },
    {
        "day": "07/16",
        "hour": "03",
        "main": {
            "feels_like": 23.55,
            "grnd_level": 997,
            "humidity": 81,
            "pressure": 1007,
            "sea_level": 1007,
            "temp": 21.36,
            "temp_kf": 0,
            "temp_max": 21.36,
            "temp_min": 21.36
        },
        "time": "07/16 03",
        "weather": {
            "description": "小雨",
            "icon": "https://openweathermap.org/img/wn/10n@2x.png",
            "id": 500,
            "main": "Rain"
        }
    },
    {
        "day": "07/16",
        "hour": "06",
        "main": {
            "feels_like": 23.83,
            "grnd_level": 998,
            "humidity": 83,
            "pressure": 1008,
            "sea_level": 1008,
            "temp": 21.3,
            "temp_kf": 0,
            "temp_max": 21.3,
            "temp_min": 21.3
        },
        "time": "07/16 06",
        "weather": {
            "description": "小雨",
            "icon": "https://openweathermap.org/img/wn/10d@2x.png",
            "id": 500,
            "main": "Rain"
        }
    },
    {
        "day": "07/16",
        "hour": "09",
        "main": {
            "feels_like": 25.97,
            "grnd_level": 999,
            "humidity": 79,
            "pressure": 1009,
            "sea_level": 1009,
            "temp": 22.94,
            "temp_kf": 0,
            "temp_max": 22.94,
            "temp_min": 22.94
        },
        "time": "07/16 09",
        "weather": {
            "description": "厚い雲",
            "icon": "https://openweathermap.org/img/wn/04d@2x.png",
            "id": 804,
            "main": "Clouds"
        }
    },
    {
        "day": "07/16",
        "hour": "12",
        "main": {
            "feels_like": 26.12,
            "grnd_level": 999,
            "humidity": 78,
            "pressure": 1009,
            "sea_level": 1009,
            "temp": 23.18,
            "temp_kf": 0,
            "temp_max": 23.18,
            "temp_min": 23.18
        },
        "time": "07/16 12",
        "weather": {
            "description": "小雨",
            "icon": "https://openweathermap.org/img/wn/10d@2x.png",
            "id": 500,
            "main": "Rain"
        }
    },
    {
        "day": "07/16",
        "hour": "15",
        "main": {
            "feels_like": 26.94,
            "grnd_level": 1000,
            "humidity": 73,
            "pressure": 1009,
            "sea_level": 1009,
            "temp": 24.09,
            "temp_kf": 0,
            "temp_max": 24.09,
            "temp_min": 24.09
        },
        "time": "07/16 15",
        "weather": {
            "description": "小雨",
            "icon": "https://openweathermap.org/img/wn/10d@2x.png",
            "id": 500,
            "main": "Rain"
        }
    },
    {
        "day": "07/16",
        "hour": "18",
        "main": {
            "feels_like": 25.35,
            "grnd_level": 1000,
            "humidity": 79,
            "pressure": 1009,
            "sea_level": 1009,
            "temp": 22.7,
            "temp_kf": 0,
            "temp_max": 22.7,
            "temp_min": 22.7
        },
        "time": "07/16 18",
        "weather": {
            "description": "小雨",
            "icon": "https://openweathermap.org/img/wn/10d@2x.png",
            "id": 500,
            "main": "Rain"
        }
    },
    {
        "day": "07/16",
        "hour": "21",
        "main": {
            "feels_like": 23.85,
            "grnd_level": 1001,
            "humidity": 81,
            "pressure": 1010,
            "sea_level": 1010,
            "temp": 21.78,
            "temp_kf": 0,
            "temp_max": 21.78,
            "temp_min": 21.78
        },
        "time": "07/16 21",
        "weather": {
            "description": "小雨",
            "icon": "https://openweathermap.org/img/wn/10n@2x.png",
            "id": 500,
            "main": "Rain"
        }
    },
    {
        "day": "07/17",
        "hour": "00",
        "main": {
            "feels_like": 23.86,
            "grnd_level": 1001,
            "humidity": 80,
            "pressure": 1010,
            "sea_level": 1010,
            "temp": 21.76,
            "temp_kf": 0,
            "temp_max": 21.76,
            "temp_min": 21.76
        },
        "time": "07/17 00",
        "weather": {
            "description": "厚い雲",
            "icon": "https://openweathermap.org/img/wn/04n@2x.png",
            "id": 804,
            "main": "Clouds"
        }
    },
    {
        "day": "07/17",
        "hour": "03",
        "main": {
            "feels_like": 23.17,
            "grnd_level": 1000,
            "humidity": 78,
            "pressure": 1010,
            "sea_level": 1010,
            "temp": 21.7,
            "temp_kf": 0,
            "temp_max": 21.7,
            "temp_min": 21.7
        },
        "time": "07/17 03",
        "weather": {
            "description": "小雨",
            "icon": "https://openweathermap.org/img/wn/10n@2x.png",
            "id": 500,
            "main": "Rain"
        }
    },
    {
        "day": "07/17",
        "hour": "06",
        "main": {
            "feels_like": 23.11,
            "grnd_level": 1001,
            "humidity": 80,
            "pressure": 1010,
            "sea_level": 1010,
            "temp": 21.67,
            "temp_kf": 0,
            "temp_max": 21.67,
            "temp_min": 21.67
        },
        "time": "07/17 06",
        "weather": {
            "description": "小雨",
            "icon": "https://openweathermap.org/img/wn/10d@2x.png",
            "id": 500,
            "main": "Rain"
        }
    }
]